test/__init__.py
test/system_test.py
thegmu_nextcloud_tools/__init__.py
thegmu_nextcloud_tools/git_sync_data.py
thegmu_nextcloud_tools/script.py
thegmu_nextcloud_tools/thegmu_davfs.py
thegmu_nextcloud_tools/thegmu_log.py
thegmu_nextcloud_tools/thegmu_nextcloud_git_sync.py
thegmu_nextcloud_tools/data/thegmu_nextcloud_git_sync.template.yaml
thegmu_nextcloud_tools-0.2.0.data/scripts/thegmu_nextcloud_git_sync.py
thegmu_nextcloud_tools-0.2.0.data/scripts/thegmu_nextcloud_git_sync.sh
thegmu_nextcloud_tools-0.2.0.data/scripts/umount.davfs.thegmu.sh
thegmu_nextcloud_tools-0.2.0.dist-info/LICENSE.txt
thegmu_nextcloud_tools-0.2.0.dist-info/METADATA
thegmu_nextcloud_tools-0.2.0.dist-info/WHEEL
thegmu_nextcloud_tools-0.2.0.dist-info/top_level.txt
thegmu_nextcloud_tools-0.2.0.dist-info/RECORD
