Metadata-Version: 2.1
Name: thegmu-nextcloud-tools
Version: 0.2.0
Summary: The GMU NextCloud Tools
Home-page: https://bitbucket.org/thegmu/thegmu-nextcloud-tools
Author: Mybrid Wonderful, The GMU
License: MIT
Keywords: thegmu-nextcloud-tools,nextcloud,git
Platform: UNKNOWN
Classifier: Environment :: Console
Classifier: Development Status :: 3 - Alpha
Classifier: Intended Audience :: System Administrators
Classifier: Topic :: Utilities
Classifier: Operating System :: Unix
Classifier: License :: OSI Approved :: MIT License
Classifier: Programming Language :: Python
Classifier: Programming Language :: Python :: 3.8
Classifier: Programming Language :: Unix Shell
Requires-Dist: PyYAML
